MANIFEST.in
README.md
setup.py
dash_extra_components/SuggestionsInput.py
dash_extra_components/TableOfContents.py
dash_extra_components/__init__.py
dash_extra_components/_imports_.py
dash_extra_components/dash_extra_components.dev.js
dash_extra_components/dash_extra_components.min.js
dash_extra_components/metadata.json
dash_extra_components/package.json
dash_extra_components.egg-info/PKG-INFO
dash_extra_components.egg-info/SOURCES.txt
dash_extra_components.egg-info/dependency_links.txt
dash_extra_components.egg-info/top_level.txt