Metadata-Version: 1.0
Name: dash-extra-components
Version: 0.0.1
Summary: Extra components for dash
Home-page: https://github.com/plotly/dash-extra-components
Author: Philippe Duval philippe@plot.ly
Author-email: UNKNOWN
License: MIT
Platform: UNKNOWN
